Metadata-Version: 1.2
Name: progressspinner-ebs
Version: 0.1
Summary: Fork of kivy-garden progress spinner
Home-page: https://github.com/chintal/progressspinner-ebs
Author: Kathryn Taylee
Author-email: kived@github.com
Maintainer: Chintalagiri Shashank
Maintainer-email: shashank@chintal.in
License: UNKNOWN
Platform: UNKNOWN
